package/__init__.py
package/test_module.py
test_package_with_bump2_pipline-0.1.1.dist-info/METADATA
test_package_with_bump2_pipline-0.1.1.dist-info/WHEEL
test_package_with_bump2_pipline-0.1.1.dist-info/top_level.txt
test_package_with_bump2_pipline-0.1.1.dist-info/RECORD
